spatialgeometry/scene.cpython-310-aarch64-linux-gnu.so
spatialgeometry/__init__.py
spatialgeometry/tools/stdout_supress.py
spatialgeometry/tools/__init__.py
spatialgeometry/geom/SceneGroup.py
spatialgeometry/geom/CollisionShape.py
spatialgeometry/geom/Shape.py
spatialgeometry/geom/SceneNode.py
spatialgeometry/geom/__init__.py
spatialgeometry/core/scene.cpp
spatialgeometry/core/scene.h
spatialgeometry/core/linalg.h
spatialgeometry/core/Eigen/LU
spatialgeometry/core/Eigen/CholmodSupport
spatialgeometry/core/Eigen/Geometry
spatialgeometry/core/Eigen/Sparse
spatialgeometry/core/Eigen/Dense
spatialgeometry/core/Eigen/PaStiXSupport
spatialgeometry/core/Eigen/IterativeLinearSolvers
spatialgeometry/core/Eigen/SparseCholesky
spatialgeometry/core/Eigen/Eigenvalues
spatialgeometry/core/Eigen/Householder
spatialgeometry/core/Eigen/StdDeque
spatialgeometry/core/Eigen/Eigen
spatialgeometry/core/Eigen/QR
spatialgeometry/core/Eigen/SparseCore
spatialgeometry/core/Eigen/MetisSupport
spatialgeometry/core/Eigen/KLUSupport
spatialgeometry/core/Eigen/StdList
spatialgeometry/core/Eigen/StdVector
spatialgeometry/core/Eigen/OrderingMethods
spatialgeometry/core/Eigen/Core
spatialgeometry/core/Eigen/SVD
spatialgeometry/core/Eigen/SuperLUSupport
spatialgeometry/core/Eigen/SPQRSupport
spatialgeometry/core/Eigen/SparseQR
spatialgeometry/core/Eigen/PardisoSupport
spatialgeometry/core/Eigen/Cholesky
spatialgeometry/core/Eigen/QtAlignedMalloc
spatialgeometry/core/Eigen/UmfPackSupport
spatialgeometry/core/Eigen/Jacobi
spatialgeometry/core/Eigen/SparseLU
spatialgeometry/core/Eigen/src/LU/Determinant.h
spatialgeometry/core/Eigen/src/LU/PartialPivLU_LAPACKE.h
spatialgeometry/core/Eigen/src/LU/FullPivLU.h
spatialgeometry/core/Eigen/src/LU/InverseImpl.h
spatialgeometry/core/Eigen/src/LU/PartialPivLU.h
spatialgeometry/core/Eigen/src/LU/arch/InverseSize4.h
spatialgeometry/core/Eigen/src/CholmodSupport/CholmodSupport.h
spatialgeometry-1.1.0.dist-info/top_level.txt
spatialgeometry-1.1.0.dist-info/LICENSE
spatialgeometry-1.1.0.dist-info/RECORD
spatialgeometry-1.1.0.dist-info/METADATA
spatialgeometry-1.1.0.dist-info/WHEEL
