Metadata-Version: 2.1
Name: spatialgeometry
Version: 1.1.0
Summary: A Shape and Geometry Description Package
Author-email: Jesse Haviland <j.haviland@qut.edu.au>, Peter Corke <rvc@petercorke.com>
License: MIT License
Project-URL: homepage, https://github.com/jhavl/spatialgeometry
Project-URL: documentation, https://jhavl.github.io/spatialgeometry/
Project-URL: repository, https://github.com/jhavl/spatialgeometry
Keywords: python,robotics,robotics-toolbox,kinematics,dynamics,motion-planning,trajectory-generation,jacobian,hessian,control,simulation,robot-manipulator,mobile-robot
Classifier: Development Status :: 5 - Production/Stable
Classifier: Intended Audience :: Developers
Classifier: License :: OSI Approved :: MIT License
Classifier: Programming Language :: Python :: 3.7
Classifier: Programming Language :: Python :: 3.8
Classifier: Programming Language :: Python :: 3.9
Classifier: Programming Language :: Python :: 3.10
Classifier: Programming Language :: Python :: 3.11
Requires-Python: >=3.7
Provides-Extra: collision
Provides-Extra: dev
Provides-Extra: docs
License-File: LICENSE
